{"cameraMode":{"drawMode":0,"name":"Shaded","section":"Shading Mode"},"sceneLighting":false,"audioPlay":false,"sceneViewState":{"m_AlwaysRefresh":false,"showFog":true,"showSkybox":false,"showFlares":true,"showImageEffects":true,"showParticleSystems":true,"showVisualEffectGraphs":true,"m_FxEnabled":true},"in2DMode":false,"pivot":{"x":392.5,"y":164.5,"z":0.0},"rotation":{"x":-0.00569027429446578,"y":-0.003004760015755892,"z":-0.000017063686755136587,"w":0.9999793767929077},"size":141.42135620117188,"orthographic":false}